[{"log_count/DEBUG":"29},
{"scheduler/dequeued":"26},
{"log_count/INFO":"7},
{"downloader/response_count":"26},
{"downloader/response_status_count/200":"25},
{"response_received_count":"25},
{"scheduler/enqueued/memory":"26},
{"downloader/response_bytes":"157010},
{"start_time":"2015-12-09 20:31:02.079388},
{"scheduler/dequeued/memory":"26},
{"scheduler/enqueued":"26},
{"downloader/request_bytes":"10189},
{"request_depth_max":"4},
{"downloader/request_method_count/GET":"26},
{"item_scraped_count":"1},
{"downloader/request_count":"26},
{"downloader/response_status_count/301":"1},
{"dupefilter/filtered":"247},
{}]